setup.py
leastbot/__init__.py
leastbot/config.py
leastbot/github.py
leastbot/irc.py
leastbot/log.py
leastbot/main.py
leastbot/webserver.py
leastbot.egg-info/PKG-INFO
leastbot.egg-info/SOURCES.txt
leastbot.egg-info/dependency_links.txt
leastbot.egg-info/entry_points.txt
leastbot.egg-info/requires.txt
leastbot.egg-info/top_level.txt
leastbot/tests/__init__.py
leastbot/tests/logutil.py
leastbot/tests/mockutil.py
leastbot/tests/test_config.py
leastbot/tests/test_github.py
leastbot/tests/test_irc.py
leastbot/tests/test_log.py
leastbot/tests/test_main.py
leastbot/tests/test_webserver.py