Metadata-Version: 1.0
Name: leastbot
Version: 0.1
Summary: leastbot - Least Authority ircbot / webhook thingy.
Home-page: https://github.com/nejucomo/leastbot
Author: Nathan Wilcox
Author-email: nathan@leastauthority.com
License: GPLv3
Platform: UNKNOWN
